cli_chess/__init__.py
cli_chess/__main__.py
cli_chess/__metadata__.py
cli_chess/core/__init__.py
cli_chess/core/api/__init__.py
cli_chess/core/api/api_manager.py
cli_chess/core/api/game_state_dispatcher.py
cli_chess/core/api/incoming_event_manger.py
cli_chess/core/game/__init__.py
cli_chess/core/game/game_metadata.py
cli_chess/core/game/game_model_base.py
cli_chess/core/game/game_options.py
cli_chess/core/game/game_presenter_base.py
cli_chess/core/game/game_view_base.py
cli_chess/core/game/offline_game/__init__.py
cli_chess/core/game/offline_game/offline_game_model.py
cli_chess/core/game/offline_game/offline_game_presenter.py
cli_chess/core/game/offline_game/offline_game_view.py
cli_chess/core/game/online_game/__init__.py
cli_chess/core/game/online_game/online_game_model.py
cli_chess/core/game/online_game/online_game_presenter.py
cli_chess/core/game/online_game/online_game_view.py
cli_chess/core/game/online_game/watch_tv/__init__.py
cli_chess/core/game/online_game/watch_tv/watch_tv_model.py
cli_chess/core/game/online_game/watch_tv/watch_tv_presenter.py
cli_chess/core/game/online_game/watch_tv/watch_tv_view.py
cli_chess/core/main/__init__.py
cli_chess/core/main/main_model.py
cli_chess/core/main/main_presenter.py
cli_chess/core/main/main_view.py
cli_chess/menus/__init__.py
cli_chess/menus/menu_common.py
cli_chess/menus/menu_model.py
cli_chess/menus/menu_presenter.py
cli_chess/menus/menu_view.py
cli_chess/menus/main_menu/__init__.py
cli_chess/menus/main_menu/main_menu_model.py
cli_chess/menus/main_menu/main_menu_presenter.py
cli_chess/menus/main_menu/main_menu_view.py
cli_chess/menus/offline_games_menu/__init__.py
cli_chess/menus/offline_games_menu/offline_games_menu_model.py
cli_chess/menus/offline_games_menu/offline_games_menu_presenter.py
cli_chess/menus/offline_games_menu/offline_games_menu_view.py
cli_chess/menus/online_games_menu/__init__.py
cli_chess/menus/online_games_menu/online_games_menu_model.py
cli_chess-1.4.2.dist-info/LICENSE
cli_chess-1.4.2.dist-info/METADATA
cli_chess-1.4.2.dist-info/WHEEL
cli_chess-1.4.2.dist-info/entry_points.txt
cli_chess-1.4.2.dist-info/top_level.txt
cli_chess-1.4.2.dist-info/RECORD
