Metadata-Version: 2.1
Name: cli-chess
Version: 1.4.2
Summary: A highly customizable way to play chess in your terminal
Home-page: https://github.com/trevorbayless/cli-chess
Author: Trevor Bayless
Author-email: cli-chess@trb.simplelogin.com
License: GPL-3.0+
Keywords: chess,terminal,fairy-stockfish,stockfish,lichess,lichess.org,cli,san,uci
Classifier: License :: OSI Approved :: GNU General Public License v3 or later (GPLv3+)
Classifier: Operating System :: POSIX :: Linux
Classifier: Operating System :: Microsoft :: Windows
Classifier: Operating System :: MacOS
Classifier: Environment :: Console
Classifier: Programming Language :: Python :: 3 :: Only
Classifier: Programming Language :: Python :: 3.8
Classifier: Programming Language :: Python :: 3.9
Classifier: Programming Language :: Python :: 3.10
Classifier: Programming Language :: Python :: 3.11
Classifier: Topic :: Games/Entertainment :: Board Games
Classifier: Topic :: Games/Entertainment :: Turn Based Strategy
Classifier: Intended Audience :: End Users/Desktop
Classifier: Intended Audience :: Developers
Classifier: Natural Language :: English
Requires-Python: >=3.8
License-File: LICENSE
Requires-Dist: chess<2.0.0,>=1.9.4
Requires-Dist: berserk<0.14.0,>=0.13.1
Requires-Dist: prompt-toolkit==3.0.47
Provides-Extra: dev
Requires-Dist: pytest<8.0.0,>=7.2.1; extra == "dev"
Requires-Dist: pytest-cov<5.0.0,>=4.0.0; extra == "dev"
Requires-Dist: pytest-socket<1.0.0,>=0.6.0; extra == "dev"
Requires-Dist: flake8<7.0.0,>=5.0.4; extra == "dev"
